blockchain/__init__.py
blockchain/core.py
blockchain/utils.py
StupidBlockChain-1.0.0.dist-info/METADATA
StupidBlockChain-1.0.0.dist-info/WHEEL
StupidBlockChain-1.0.0.dist-info/top_level.txt
StupidBlockChain-1.0.0.dist-info/RECORD
