Metadata-Version: 2.1
Name: StupidBlockChain
Version: 1.0.0
Summary: Simple Python blockchain implementation.
Home-page: https://github.com/lucas-meira/blockchain
Author: Lucas Meira
Author-email: lima07.lucas@gmail.com
Project-URL: Source, https://github.com/lucas-meira/blockchain
Classifier: Operating System :: OS Independent
Classifier: Programming Language :: Python
Classifier: Topic :: Software Development
Requires-Python: >=3.6
Requires-Dist: colorama
